maidr/__init__.py
maidr/api.py
maidr/core/__init__.py
maidr/core/context_manager.py
maidr/core/figure_manager.py
maidr/core/maidr.py
maidr/core/enum/__init__.py
maidr/core/enum/library.py
maidr/core/enum/maidr_key.py
maidr/core/enum/plot_type.py
maidr/core/enum/smooth_keywords.py
maidr/core/plot/__init__.py
maidr/core/plot/barplot.py
maidr/core/plot/boxplot.py
maidr/core/plot/candlestick.py
maidr/core/plot/grouped_barplot.py
maidr/core/plot/heatmap.py
maidr/core/plot/histogram.py
maidr/core/plot/lineplot.py
maidr/core/plot/maidr_plot.py
maidr/core/plot/maidr_plot_factory.py
maidr/core/plot/mplfinance_barplot.py
maidr/core/plot/mplfinance_lineplot.py
maidr/core/plot/regplot.py
maidr/core/plot/scatterplot.py
maidr/exception/__init__.py
maidr/exception/extraction_error.py
maidr/patch/__init__.py
maidr/patch/barplot.py
maidr/patch/boxplot.py
maidr/patch/candlestick.py
maidr/patch/clear.py
maidr/patch/common.py
maidr/patch/heatmap.py
maidr/patch/highlight.py
maidr/patch/histogram.py
maidr/patch/kdeplot.py
maidr/patch/lineplot.py
maidr/patch/mplfinance.py
maidr/patch/regplot.py
maidr/patch/scatterplot.py
maidr/util/__init__.py
maidr/util/datetime_conversion.py
maidr/util/dedup_utils.py
maidr/util/environment.py
maidr/util/mplfinance_utils.py
maidr/util/plot_detection.py
maidr/util/regression_line_utils.py
maidr/util/svg_utils.py
maidr/util/mixin/__init__.py
maidr/util/mixin/extractor_mixin.py
maidr/util/mixin/merger_mixin.py
maidr/widget/__init__.py
maidr/widget/shiny.py
maidr-1.10.0.dist-info/METADATA
maidr-1.10.0.dist-info/WHEEL
maidr-1.10.0.dist-info/licenses/LICENSE
maidr-1.10.0.dist-info/RECORD
